heimdall_logger/__init__.py
heimdall_logger/constants/__init__.py
heimdall_logger/constants/log_level.py
heimdall_logger/constants/log_output_format.py
heimdall_logger/format_log/__init__.py
heimdall_logger/format_log/template.py
heimdall_logger/handlers/__init__.py
heimdall_logger/handlers/handle_data.py
heimdall_logger/handlers/handle_log.py
heimdall_logger/loggers/__init__.py
heimdall_logger/loggers/async_logger.py
heimdall_logger/loggers/sync_logger.py
heimdall_logger/providers/__init__.py
heimdall_logger/providers/api/__init__.py
heimdall_logger/providers/api/async_callback_provider.py
heimdall_logger/providers/log_file_system/__init__.py
heimdall_logger/providers/log_file_system/filesystem_provider.py
heimdall_logger/utils/__init__.py
heimdall_logger/utils/probe.py
tests/__init__.py
heimdall_logger-0.1.2.dist-info/LICENSE
heimdall_logger-0.1.2.dist-info/METADATA
heimdall_logger-0.1.2.dist-info/WHEEL
heimdall_logger-0.1.2.dist-info/top_level.txt
heimdall_logger-0.1.2.dist-info/RECORD
