Metadata-Version: 2.1
Name: heimdall-logger
Version: 0.1.2
Summary: Asynchronous logging lib
Home-page: https://github.com/giovannifarlley/heimdall-logger
Author: Farlley Ferreira
Author-email: farlley@live.com
License: MIT
Keywords: dev,log,async,aiologger,
Platform: UNKNOWN
Classifier: Intended Audience :: Developers
Classifier: License :: OSI Approved :: MIT License
Classifier: Natural Language :: English
Classifier: Programming Language :: Python :: 3
Requires-Python: >=3.8
Requires-Dist: aiofiles
Requires-Dist: aiohttp
